html_form_to_dict/__init__.py
html_form_to_dict/tests/__init__.py
html_form_to_dict/tests/test_html_form_to_dict.py
html_form_to_dict-2022.10.1.dist-info/LICENSE
html_form_to_dict-2022.10.1.dist-info/METADATA
html_form_to_dict-2022.10.1.dist-info/WHEEL
html_form_to_dict-2022.10.1.dist-info/top_level.txt
html_form_to_dict-2022.10.1.dist-info/RECORD
