Metadata-Version: 2.1
Name: html-form-to-dict
Version: 2022.10.1
Summary: Parse HTML to a Python Dictionary
Home-page: https://github.com/guettli/html_form_to_dict
Author: Thomas Güttler
Author-email: info.html_form_to_dict@thomas-guettler.de
Classifier: Environment :: Web Environment
Classifier: License :: OSI Approved :: MIT License
Classifier: Operating System :: OS Independent
Classifier: Programming Language :: Python :: 3
Classifier: Programming Language :: Python :: 2.7
Requires-Python: >=2.7
License-File: LICENSE
Requires-Dist: lxml
Provides-Extra: test
Requires-Dist: pytest ; extra == 'test'
